simple_currency_converter/__init__.py
simple_currency_converter/__main__.py
simple_currency_converter/core.py
simple_currency_converter/currency_codes.py
simple_currency_converter-0.1.2.dist-info/METADATA
simple_currency_converter-0.1.2.dist-info/WHEEL
simple_currency_converter-0.1.2.dist-info/entry_points.txt
simple_currency_converter-0.1.2.dist-info/top_level.txt
simple_currency_converter-0.1.2.dist-info/RECORD
