Metadata-Version: 2.4
Name: simple_currency_converter
Version: 0.1.2
Summary: Simple currency converter
Requires-Python: >=3.6
Requires-Dist: requests
Requires-Dist: types-requests
Requires-Dist: pytest
Requires-Dist: pytest-cov
